README
setup.py
tornado_extensions/__init__.py
tornado_extensions/concurrency.py
tornado_extensions/conf.py
tornado_extensions/ioloop.py
tornado_extensions/utils.py
tornado_extensions/cache/__init__.py
tornado_extensions/cache/backends/__init__.py
tornado_extensions/cache/backends/base.py
tornado_extensions/cache/backends/memcached.py
tornado_extensions/celery/__init__.py
tornado_extensions/celery/http.py
tornado_extensions/sessions/__init__.py
tornado_extensions/sessions/middlewares.py
tornado_extensions/sessions/utils.py
tornado_extensions/sessions/backends/__init__.py
tornado_extensions/sessions/backends/base.py
tornado_extensions/sessions/backends/cache.py
tornado_extensions/sockjs/__init__.py
tornado_extensions/sockjs/conn.py
tornado_extensions/sockjs/mixins.py
tornado_extensions/sockjs/router.py
tornado_exts.egg-info/PKG-INFO
tornado_exts.egg-info/SOURCES.txt
tornado_exts.egg-info/dependency_links.txt
tornado_exts.egg-info/not-zip-safe
tornado_exts.egg-info/top_level.txt