Metadata-Version: 1.1
Name: tornado-exts
Version: 0.0.3
Summary: A python module that contain common definitions for Django and Tornado game project
Home-page: https://bitbucket.org/Rustem/iogame-tor-exts
Author: Rustem Kamun, German Ilyin, Cool Max
Author-email: r.kamun@gmail.com
License: MIT
Keywords: django tornado common
Platform: UNKNOWN
Classifier: Development Status :: 5 - Production/Stable
Classifier: Intended Audience :: Developers
Classifier: License :: OSI Approved :: MIT License
Classifier: Topic :: Software Development :: Build Tools
Classifier: Programming Language :: Python :: 2.7
